surfing_python-0.1.2.dist-info/METADATA
surfing_python-0.1.2.dist-info/WHEEL
surfing_python-0.1.2.dist-info/licenses/LICENSE
surfing_python.pyi
surfing_python/__init__.py
surfing_python/__init__.pyi
surfing_python/py.typed
surfing_python/surfing_python.cpython-39-darwin.so
surfing_python-0.1.2.dist-info/RECORD
